ms_toolkit/__init__.py
ms_toolkit/api.py
ms_toolkit/io.py
ms_toolkit/models.py
ms_toolkit/preprocessing.py
ms_toolkit/preselector.py
ms_toolkit/similarity.py
ms_toolkit/w2v.py
ms_toolkit_nrel-0.1.2.dist-info/licenses/LICENSE
ms_toolkit_nrel-0.1.2.dist-info/METADATA
ms_toolkit_nrel-0.1.2.dist-info/WHEEL
ms_toolkit_nrel-0.1.2.dist-info/top_level.txt
ms_toolkit_nrel-0.1.2.dist-info/RECORD
