Metadata-Version: 2.4
Name: ms-toolkit-nrel
Version: 0.1.2
Summary: Tools for mass spectrometry data analysis
License: Apache-2.0
Requires-Python: >=3.8
License-File: LICENSE
Requires-Dist: numpy
Requires-Dist: joblib
Requires-Dist: gensim
Requires-Dist: scikit-learn
Requires-Dist: requests
Requires-Dist: tqdm
Provides-Extra: ui
Requires-Dist: customtkinter; extra == "ui"
Requires-Dist: PySide6; extra == "ui"
Provides-Extra: ctk
Requires-Dist: customtkinter; extra == "ctk"
Provides-Extra: pyside
Requires-Dist: PySide6; extra == "pyside"
Dynamic: description
Dynamic: description-content-type
Dynamic: license
Dynamic: license-file
Dynamic: provides-extra
Dynamic: requires-dist
Dynamic: requires-python
Dynamic: summary
